lukes_awesome_package/__init__.py
lukes_awesome_package/main.py
lukes_awesome_package-0.0.1.dist-info/LICENSE
lukes_awesome_package-0.0.1.dist-info/METADATA
lukes_awesome_package-0.0.1.dist-info/WHEEL
lukes_awesome_package-0.0.1.dist-info/top_level.txt
lukes_awesome_package-0.0.1.dist-info/RECORD
