Metadata-Version: 2.1
Name: lukes_awesome_package
Version: 0.0.1
Summary: A awesome example package
Author-email: Luke Neuendorf <lukeneuendorf@gmail.com>
Classifier: Programming Language :: Python :: 3
Classifier: License :: OSI Approved :: MIT License
Classifier: Operating System :: OS Independent
Requires-Python: >=3.8
License-File: LICENSE
